LICENSE
README.md
setup.py
tests/tiruka_fib_py/__init__.py
tests/tiruka_fib_py/fib_calcs/__init__.py
tests/tiruka_fib_py/fib_calcs/test_fib_number.py
tests/tiruka_fib_py/fib_calcs/test_fib_numbers.py
tiruka_fib_py/__init__.py
tiruka_fib_py/version.py
tiruka_fib_py.egg-info/PKG-INFO
tiruka_fib_py.egg-info/SOURCES.txt
tiruka_fib_py.egg-info/dependency_links.txt
tiruka_fib_py.egg-info/entry_points.txt
tiruka_fib_py.egg-info/requires.txt
tiruka_fib_py.egg-info/top_level.txt
tiruka_fib_py/cmd/__init__.py
tiruka_fib_py/cmd/fib_numb.py
tiruka_fib_py/fib_calcs/__init__.py
tiruka_fib_py/fib_calcs/fib_number.py
tiruka_fib_py/fib_calcs/fib_numbers.py