Metadata-Version: 2.1
Name: tiruka-fib-py
Version: 0.0.2
Summary: Calculates a Fibonacci number
Home-page: https://github.com/tiruka/fib-py
Author: tiruka
Author-email: tiruka.engineer@gmail.com
License: UNKNOWN
Platform: UNKNOWN
Classifier: Development Status :: 4 - Beta
Classifier: Programming Language :: Python :: 3
Classifier: Operating System :: OS Independent
Provides-Extra: server
License-File: LICENSE
